autogen_agentchat/__init__.py
autogen_agentchat/messages.py
autogen_agentchat/py.typed
autogen_agentchat/agents/__init__.py
autogen_agentchat/agents/_assistant_agent.py
autogen_agentchat/agents/_base_chat_agent.py
autogen_agentchat/agents/_code_executor_agent.py
autogen_agentchat/agents/_message_filter_agent.py
autogen_agentchat/agents/_society_of_mind_agent.py
autogen_agentchat/agents/_user_proxy_agent.py
autogen_agentchat/base/__init__.py
autogen_agentchat/base/_chat_agent.py
autogen_agentchat/base/_handoff.py
autogen_agentchat/base/_task.py
autogen_agentchat/base/_team.py
autogen_agentchat/base/_termination.py
autogen_agentchat/conditions/__init__.py
autogen_agentchat/conditions/_terminations.py
autogen_agentchat/state/__init__.py
autogen_agentchat/state/_states.py
autogen_agentchat/teams/__init__.py
autogen_agentchat/teams/_group_chat/__init__.py
autogen_agentchat/teams/_group_chat/_base_group_chat.py
autogen_agentchat/teams/_group_chat/_base_group_chat_manager.py
autogen_agentchat/teams/_group_chat/_chat_agent_container.py
autogen_agentchat/teams/_group_chat/_events.py
autogen_agentchat/teams/_group_chat/_round_robin_group_chat.py
autogen_agentchat/teams/_group_chat/_selector_group_chat.py
autogen_agentchat/teams/_group_chat/_sequential_routed_agent.py
autogen_agentchat/teams/_group_chat/_swarm_group_chat.py
autogen_agentchat/teams/_group_chat/_graph/__init__.py
autogen_agentchat/teams/_group_chat/_graph/_digraph_group_chat.py
autogen_agentchat/teams/_group_chat/_graph/_graph_builder.py
autogen_agentchat/teams/_group_chat/_magentic_one/__init__.py
autogen_agentchat/teams/_group_chat/_magentic_one/_magentic_one_group_chat.py
autogen_agentchat/teams/_group_chat/_magentic_one/_magentic_one_orchestrator.py
autogen_agentchat/teams/_group_chat/_magentic_one/_prompts.py
autogen_agentchat/tools/__init__.py
autogen_agentchat/tools/_agent.py
autogen_agentchat/tools/_task_runner_tool.py
autogen_agentchat/tools/_team.py
autogen_agentchat/ui/__init__.py
autogen_agentchat-0.7.0.dist-info/METADATA
autogen_agentchat-0.7.0.dist-info/WHEEL
autogen_agentchat-0.7.0.dist-info/licenses/LICENSE-CODE
autogen_agentchat-0.7.0.dist-info/RECORD
