Metadata-Version: 2.4
Name: autogen-agentchat
Version: 0.7.0
Summary: AutoGen agents and teams library
License:     MIT License
License-File: LICENSE-CODE
Classifier: License :: OSI Approved :: MIT License
Classifier: Operating System :: OS Independent
Classifier: Programming Language :: Python :: 3
Requires-Python: >=3.10
Requires-Dist: autogen-core==0.7.0
